CHANGES.rst
LICENSE.txt
README.rst
setup.cfg
setup.py
nose2django/__init__.py
nose2django/config.py
nose2django/nose2django.py
nose2django.egg-info/PKG-INFO
nose2django.egg-info/SOURCES.txt
nose2django.egg-info/dependency_links.txt
nose2django.egg-info/requires.txt
nose2django.egg-info/top_level.txt