Metadata-Version: 1.1
Name: nose2django
Version: 0.1.2
Summary: Nose2 plugin to run django tests through nose2 instead of the django test runner.
Home-page: https://github.com/bretth/nose2django
Author: Brett Haydon
Author-email: brett@haydon.id.au
License: BSD
Keywords: nose2
Platform: UNKNOWN
Classifier: Development Status :: 3 - Alpha
Classifier: Environment :: Plugins
Classifier: Framework :: Django
Classifier: Intended Audience :: Developers
Classifier: License :: OSI Approved :: BSD License
Classifier: Operating System :: OS Independent
Classifier: Programming Language :: Python :: 2.7
Classifier: Programming Language :: Python :: 3.3
Classifier: Topic :: Software Development :: Testing
